anybyte_utils/__init__.py
anybyte_utils/mongo.py
anybyte_utils/mongo_schemas.py
anybyte_utils/s3linker.py
anybyte_utils/secrets.py
anybyte_utils-1.0.0.dist-info/METADATA
anybyte_utils-1.0.0.dist-info/WHEEL
anybyte_utils-1.0.0.dist-info/top_level.txt
anybyte_utils-1.0.0.dist-info/RECORD
