Metadata-Version: 2.1
Name: anybyte-utils
Version: 1.0.0
Summary: Anybyte developer utils
Author: Anybyte
Author-email: <ben@anybyte.ai>
Keywords: python,anybyte,utils,developer
Classifier: Development Status :: 1 - Planning
Classifier: Intended Audience :: Developers
Classifier: Programming Language :: Python :: 3
Classifier: Operating System :: Unix
Classifier: Operating System :: MacOS :: MacOS X
Classifier: Operating System :: Microsoft :: Windows
Requires-Dist: boto3
